log_loss_tool/__init__.py
log_loss_tool/log_loss.py
log_loss_tool-0.2.0.dist-info/LICENSE
log_loss_tool-0.2.0.dist-info/METADATA
log_loss_tool-0.2.0.dist-info/WHEEL
log_loss_tool-0.2.0.dist-info/top_level.txt
log_loss_tool-0.2.0.dist-info/RECORD
