Metadata-Version: 2.1
Name: log_loss_tool
Version: 0.2.0
Summary: A Python library to visualize and calculate Log-Loss, including optimal threshold calculation.
Home-page: https://github.com/RodrigoCamposDS/log_loss_tool
Author: Rodrigo Campos
Author-email: rodrigocamposag90@gmail.com
Classifier: Programming Language :: Python :: 3
Classifier: License :: OSI Approved :: MIT License
Classifier: Operating System :: OS Independent
Requires-Python: >=3.6
License-File: LICENSE
Requires-Dist: numpy>=1.21.0
Requires-Dist: matplotlib>=3.4.0
